econia_sdk/README.md
econia_sdk/__init__.py
econia_sdk/entry/__init__.py
econia_sdk/entry/incentives.py
econia_sdk/entry/market.py
econia_sdk/entry/registry.py
econia_sdk/entry/user.py
econia_sdk/lib.py
econia_sdk/types.py
econia_sdk/utils/__init__.py
econia_sdk/utils/decimals.py
econia_sdk/view/__init__.py
econia_sdk/view/incentives.py
econia_sdk/view/market.py
econia_sdk/view/registry.py
econia_sdk/view/resource_account.py
econia_sdk/view/user.py
econia_sdk-2.1.0.dist-info/METADATA
econia_sdk-2.1.0.dist-info/WHEEL
econia_sdk-2.1.0.dist-info/entry_points.txt
econia_sdk-2.1.0.dist-info/RECORD
